[{"senderKeyId":1186751427,"senderChainKey":{"iteration":251,"seed":"mh3dKz8V14w1Pc9GQH3aUFACsZ2X6/DiBXvGtT8LzwY="},"senderSigningKey":{"public":"BdvKkCiCHqdXRN36t2yoSmoQ7UKL3mATbslFhT0ntQpp","private":"yLSm4WvB1Q08rSKKrg2ZyLAnfF6PLCQM3Is4vToDKnM="},"senderMessageKeys":[{},{},{},{},{},{},{},{},{},{},{},{},{},{},{},{},{},{},{},{},{},{},{},{},{},{},{},{},{},{},{},{},{},{},{},{},{},{},{},{},{},{},{},{},{},{},{},{},{},{},{},{},{},{},{},{},{},{},{},{},{},{},{},{},{},{},{},{},{},{},{},{},{},{},{},{},{},{},{},{},{},{},{},{},{},{},{},{},{},{},{},{},{},{},{},{},{},{},{},{},{},{},{},{},{},{},{},{},{},{},{},{},{},{},{},{},{},{},{},{},{},{},{},{},{}]}]