[{"senderKeyId":204107979,"senderChainKey":{"iteration":305,"seed":"mKMa/fiB9TjHrkjcbWHia19gjXgJm2tJo/R0yg3CkGY="},"senderSigningKey":{"public":"BR4Lm7M+qroF1ydNF4v7S9Z3lwNeP0wIzdYc667VuR4E"},"senderMessageKeys":[{},{},{},{},{},{},{},{},{},{},{},{},{},{},{},{},{},{},{},{},{},{},{},{},{},{},{},{},{},{},{},{},{},{},{},{},{},{},{},{},{},{},{},{},{},{},{},{},{},{},{},{},{},{},{},{},{},{},{},{},{},{},{},{},{},{},{},{},{},{},{},{},{},{},{},{},{},{},{},{},{},{},{},{},{},{},{},{},{},{},{},{},{},{},{},{},{},{},{},{},{},{},{},{},{},{},{},{},{},{},{},{},{},{},{},{},{},{},{},{},{},{},{},{},{},{},{},{},{},{},{},{},{},{},{}]},{"senderKeyId":204107979,"senderChainKey":{"iteration":45,"seed":"5CipxC6H8H30gD6vvt86VGzXxoslpK70mnPsKKXgkr0="},"senderSigningKey":{"public":"BR4Lm7M+qroF1ydNF4v7S9Z3lwNeP0wIzdYc667VuR4E"},"senderMessageKeys":[]},{"senderKeyId":204107979,"senderChainKey":{"iteration":255,"seed":"EmGfYWMcUGzb46nh9ve6SVdKGghoO1XOL0/g357YTo4="},"senderSigningKey":{"public":"BR4Lm7M+qroF1ydNF4v7S9Z3lwNeP0wIzdYc667VuR4E"},"senderMessageKeys":[]},{"senderKeyId":204107979,"senderChainKey":{"iteration":259,"seed":"nS7xyvdOBsUPazHq6HEO9fkYQ/lg3ia60VXZ7ytyZjI="},"senderSigningKey":{"public":"BR4Lm7M+qroF1ydNF4v7S9Z3lwNeP0wIzdYc667VuR4E"},"senderMessageKeys":[]}]