[{"senderKeyId":1186751427,"senderChainKey":{"iteration":153,"seed":"v9knhMIW4DDM6Tm3eYyhsLSHVHye49LgTBYhhKrlZVY="},"senderSigningKey":{"public":"BdvKkCiCHqdXRN36t2yoSmoQ7UKL3mATbslFhT0ntQpp","private":"yLSm4WvB1Q08rSKKrg2ZyLAnfF6PLCQM3Is4vToDKnM="},"senderMessageKeys":[{},{},{},{},{},{},{},{},{},{},{},{},{},{},{},{},{},{},{},{},{},{},{},{},{},{},{},{},{},{},{},{},{},{},{},{},{},{},{},{},{},{},{},{},{},{},{},{},{},{},{},{},{},{},{},{},{},{},{},{},{},{},{},{},{},{},{},{},{},{},{},{},{},{},{},{}]}]